[
  {
    "text": "best",
    "value": 6810
  },
  {
    "text": "for",
    "value": 6106
  },
  {
    "text": "what",
    "value": 5759
  },
  {
    "text": "how",
    "value": 4754
  },
  {
    "text": "dekat",
    "value": 4303
  },
  {
    "text": "sedap",
    "value": 2838
  },
  {
    "text": "savings",
    "value": 2813
  },
  {
    "text": "you",
    "value": 2800
  },
  {
    "text": "makan",
    "value": 2472
  },
  {
    "text": "kat",
    "value": 2455
  },
  {
    "text": "near",
    "value": 2210
  },
  {
    "text": "with",
    "value": 2178
  },
  {
    "text": "around",
    "value": 2167
  },
  {
    "text": "road",
    "value": 2133
  },
  {
    "text": "budget",
    "value": 1963
  },
  {
    "text": "hotel",
    "value": 1908
  },
  {
    "text": "murah",
    "value": 1898
  },
  {
    "text": "where",
    "value": 1889
  },
  {
    "text": "money",
    "value": 1874
  },
  {
    "text": "spending",
    "value": 1767
  },
  {
    "text": "this",
    "value": 1747
  },
  {
    "text": "about",
    "value": 1543
  },
  {
    "text": "balance",
    "value": 1489
  },
  {
    "text": "recommendation",
    "value": 1451
  },
  {
    "text": "place",
    "value": 1405
  },
  {
    "text": "recommend",
    "value": 1400
  },
  {
    "text": "did",
    "value": 1397
  },
  {
    "text": "the",
    "value": 1376
  },
  {
    "text": "yang",
    "value": 1373
  },
  {
    "text": "tell",
    "value": 1369
  },
  {
    "text": "restaurant",
    "value": 1339
  },
  {
    "text": "much",
    "value": 1331
  },
  {
    "text": "are",
    "value": 1331
  },
  {
    "text": "advice",
    "value": 1296
  },
  {
    "text": "save",
    "value": 1291
  },
  {
    "text": "month",
    "value": 1265
  },
  {
    "text": "expenses",
    "value": 1265
  },
  {
    "text": "can",
    "value": 1220
  },
  {
    "text": "tips",
    "value": 1212
  },
  {
    "text": "why",
    "value": 1144
  },
  {
    "text": "help",
    "value": 1136
  },
  {
    "text": "start",
    "value": 1098
  },
  {
    "text": "debt",
    "value": 1085
  },
  {
    "text": "give",
    "value": 1067
  },
  {
    "text": "good",
    "value": 1025
  },
  {
    "text": "food",
    "value": 1011
  },
  {
    "text": "salary",
    "value": 997
  },
  {
    "text": "tempat",
    "value": 983
  },
  {
    "text": "cafe",
    "value": 979
  },
  {
    "text": "way",
    "value": 976
  },
  {
    "text": "rate",
    "value": 966
  },
  {
    "text": "aku",
    "value": 960
  },
  {
    "text": "income",
    "value": 958
  },
  {
    "text": "eat",
    "value": 956
  },
  {
    "text": "add",
    "value": 955
  },
  {
    "text": "kedai",
    "value": 946
  },
  {
    "text": "stay",
    "value": 943
  },
  {
    "text": "analysis",
    "value": 922
  },
  {
    "text": "makanan",
    "value": 914
  },
  {
    "text": "kuala",
    "value": 889
  },
  {
    "text": "explain",
    "value": 888
  },
  {
    "text": "tapah",
    "value": 884
  },
  {
    "text": "week",
    "value": 876
  },
  {
    "text": "should",
    "value": 854
  },
  {
    "text": "who",
    "value": 851
  },
  {
    "text": "last",
    "value": 845
  },
  {
    "text": "2025",
    "value": 815
  },
  {
    "text": "guide",
    "value": 800
  },
  {
    "text": "malaysia",
    "value": 784
  },
  {
    "text": "fund",
    "value": 770
  },
  {
    "text": "strategies",
    "value": 748
  },
  {
    "text": "spend",
    "value": 739
  },
  {
    "text": "which",
    "value": 720
  },
  {
    "text": "idea",
    "value": 720
  },
  {
    "text": "interest",
    "value": 711
  },
  {
    "text": "app",
    "value": 708
  },
  {
    "text": "nak",
    "value": 703
  },
  {
    "text": "does",
    "value": 698
  },
  {
    "text": "inflation",
    "value": 697
  },
  {
    "text": "pay",
    "value": 683
  },
  {
    "text": "thoughts",
    "value": 676
  },
  {
    "text": "pros",
    "value": 675
  },
  {
    "text": "and",
    "value": 671
  },
  {
    "text": "compare",
    "value": 669
  },
  {
    "text": "cons",
    "value": 668
  },
  {
    "text": "name",
    "value": 658
  },
  {
    "text": "worth",
    "value": 655
  },
  {
    "text": "outlook",
    "value": 650
  },
  {
    "text": "saving",
    "value": 646
  },
  {
    "text": "prediction",
    "value": 641
  },
  {
    "text": "better",
    "value": 637
  },
  {
    "text": "emergency",
    "value": 634
  },
  {
    "text": "check",
    "value": 623
  },
  {
    "text": "think",
    "value": 619
  },
  {
    "text": "saved",
    "value": 601
  },
  {
    "text": "transaction",
    "value": 599
  },
  {
    "text": "opinion",
    "value": 597
  },
  {
    "text": "bear",
    "value": 589
  },
  {
    "text": "besut",
    "value": 587
  },
  {
    "text": "terengganu",
    "value": 587
  }
]